chatgpt/__init__.py
chatgpt/__main__.py
chatgpt/authentication.py
chatgpt/chatgpt.py
chatgpt/errors.py
chatgpt/sessions.py
chatgpt/utils.py
chatgpt/cli/__init__.py
chatgpt/cli/__main__.py
chatgpt/cli/custom_rich.py
chatgpt/package_name/__init__.py
chatgpt/package_name/chatgpt.py
chatgpt-2.2214.0.dist-info/LICENSE
chatgpt-2.2214.0.dist-info/METADATA
chatgpt-2.2214.0.dist-info/WHEEL
chatgpt-2.2214.0.dist-info/entry_points.txt
chatgpt-2.2214.0.dist-info/top_level.txt
chatgpt-2.2214.0.dist-info/RECORD
